ducky_converter.py
main.py
devices/__init__.py
devices/android.py
devices/arduino_leonardo.py
devices/device_manager.py
devices/digispark.py
devices/esp32.py
devices/evilcrow_cable_wind.py
devices/raspberry_pi_pico.py
devices/teensy_4.py
devices/xiao_rp2040.py
happy_frog_parser/__init__.py
happy_frog_parser/_version.py
happy_frog_parser/encoder.py
happy_frog_parser/parser.py
payloads/__init__.py
payloads/android_automation_demo.txt
payloads/android_mixed_test.txt
payloads/android_test.txt
payloads/automated_system_setup.txt
payloads/ducky.txt
payloads/ducky_converted.txt
payloads/evilcrow_android_test.txt
payloads/evilcrow_test.txt
payloads/hello_world.txt
payloads/my_first_script.txt
payloads/redteam_initial_access.txt
payloads/safe_android_test.txt
tests/__init__.py
happy_frog-0.2.7.dist-info/LICENSE
happy_frog-0.2.7.dist-info/METADATA
happy_frog-0.2.7.dist-info/WHEEL
happy_frog-0.2.7.dist-info/entry_points.txt
happy_frog-0.2.7.dist-info/top_level.txt
happy_frog-0.2.7.dist-info/RECORD
