Metadata-Version: 2.1
Name: happy-frog
Version: 0.2.7
Summary: Educational HID emulation framework for cybersecurity learning
Home-page: https://github.com/ZeroDumb/happy-frog
Author: ZeroDumb
Author-email: zero@zerodumb.dev
License: GNU General Public License v3
Project-URL: Bug Reports, https://github.com/ZeroDumb/happy-frog/issues
Project-URL: Source, https://github.com/ZeroDumb/happy-frog
Project-URL: Documentation, https://github.com/ZeroDumb/happy-frog/tree/main/docs
Project-URL: Homepage, https://zerodumb.dev
Keywords: cybersecurity,education,hid,ducky,microcontroller,circuitpython,automation,scripting,educational,ethical,open source,free,gplv3,froggy basher,happy frog
Classifier: Development Status :: 4 - Beta
Classifier: Intended Audience :: Education
Classifier: Intended Audience :: Information Technology
Classifier: Operating System :: OS Independent
Classifier: Programming Language :: Python :: 3
Classifier: Programming Language :: Python :: 3.7
Classifier: Programming Language :: Python :: 3.8
Classifier: Programming Language :: Python :: 3.9
Classifier: Programming Language :: Python :: 3.10
Classifier: Programming Language :: Python :: 3.11
Classifier: Programming Language :: Python :: 3.12
Classifier: Programming Language :: Python :: 3.13
Classifier: Topic :: Education
Classifier: Topic :: Security
Classifier: Topic :: Software Development :: Libraries :: Python Modules
Classifier: Topic :: System :: Hardware
Classifier: Topic :: System :: Emulators
Requires-Python: >=3.7
License-File: LICENSE
Requires-Dist: click >=8.0.0
Requires-Dist: colorama >=0.4.4
